relationship_structure_identification/__init__.py
relationship_structure_identification/grouping_identification.py
relationship_structure_identification/performance_metrics.py
relationship_structure_identification/simulations.py
relationship_structure_identification/visualization.py
relationship_structure_identification-0.0.1.dist-info/LICENSE
relationship_structure_identification-0.0.1.dist-info/METADATA
relationship_structure_identification-0.0.1.dist-info/WHEEL
relationship_structure_identification-0.0.1.dist-info/top_level.txt
relationship_structure_identification-0.0.1.dist-info/RECORD
