Metadata-Version: 2.1
Name: relationship_structure_identification
Version: 0.0.1
Summary: Implementation of our method for identifying the relationship structure among multiple datasets
Home-page: https://github.com/SSTGroup/relationship_structure_identification
Author: Isabell Lehmann
Author-email: isabell.lehmann@sst.upb.de
License: LICENSE
Keywords: independent vector analysis,
Classifier: Programming Language :: Python :: 3
Classifier: License :: OSI Approved :: MIT License
Classifier: Operating System :: OS Independent
Requires-Python: >=3.10
License-File: LICENSE
Requires-Dist: numpy
Requires-Dist: scipy
Requires-Dist: pytest
Requires-Dist: matplotlib
Requires-Dist: independent-vector-analysis
Requires-Dist: argparse
Requires-Dist: scikit-learn
Requires-Dist: pathlib
